preaudio/__init__.py
preaudio/core.py
preaudio-0.1.0.dist-info/licenses/LICENSE
preaudio-0.1.0.dist-info/METADATA
preaudio-0.1.0.dist-info/WHEEL
preaudio-0.1.0.dist-info/top_level.txt
preaudio-0.1.0.dist-info/RECORD
