Metadata-Version: 2.4
Name: preaudio
Version: 0.1.0
Summary: A small audio visualization library built from Jupyter Notebook code.
Home-page: https://github.com/Nirvik34/preaudio
Author: Nirvik Goswami
Author-email: nirvikgoswami689@gmail.com
Classifier: Programming Language :: Python :: 3
Classifier: License :: OSI Approved :: MIT License
Requires-Python: >=3.7
License-File: LICENSE
Requires-Dist: numpy
Requires-Dist: pandas
Requires-Dist: matplotlib
Requires-Dist: seaborn
Requires-Dist: librosa
Dynamic: author
Dynamic: author-email
Dynamic: classifier
Dynamic: description
Dynamic: description-content-type
Dynamic: home-page
Dynamic: license-file
Dynamic: requires-dist
Dynamic: requires-python
Dynamic: summary
